setup.py
telegraphapi/__init__.py
telegraphapi/exceptions.py
telegraphapi/main.py
telegraphapi/utils.py
telegraphapi.egg-info/PKG-INFO
telegraphapi.egg-info/SOURCES.txt
telegraphapi.egg-info/dependency_links.txt
telegraphapi.egg-info/not-zip-safe
telegraphapi.egg-info/requires.txt
telegraphapi.egg-info/top_level.txt