Metadata-Version: 1.1
Name: telegraphapi
Version: 0.5
Summary: Python TelegraphAPI wrapper
Home-page: https://github.com/MonsterDeveloper/python-telegraphapi
Author: Andrew Developer
Author-email: slider7259@gmail.com
License: MIT
Keywords: telegraph api rest http telegraphapi telegram
Platform: UNKNOWN
Classifier: License :: OSI Approved :: MIT License
Classifier: Development Status :: 4 - Beta
Classifier: Operating System :: OS Independent
Classifier: Programming Language :: Python
Classifier: Programming Language :: Python :: 2
Classifier: Programming Language :: Python :: 2.7
Classifier: Programming Language :: Python :: 3
Classifier: Programming Language :: Python :: 3.4
Classifier: Programming Language :: Python :: 3.5
Classifier: Programming Language :: Python :: Implementation :: PyPy
Classifier: Programming Language :: Python :: Implementation :: CPython
